README.md
setup.py
nonebot_tuling/__init__.py
nonebot_tuling.egg-info/PKG-INFO
nonebot_tuling.egg-info/SOURCES.txt
nonebot_tuling.egg-info/dependency_links.txt
nonebot_tuling.egg-info/requires.txt
nonebot_tuling.egg-info/top_level.txt