Metadata-Version: 2.1
Name: nonebot-tuling
Version: 1.0.1
Summary: A NoneBot plugin that provides Tuling's chatting function
Home-page: https://github.com/richardchien/nonebot-tuling
Author: Richard Chien
Author-email: richardchienthebest@gmail.com
License: MIT License
Platform: UNKNOWN
